MANIFEST.in
README.rst
pytest.ini
setup.cfg
setup.py
contrib/maxima/abarbanel-pml.mac
contrib/maxima/bgk-flow.mac
contrib/maxima/bilinearmap.mac
contrib/maxima/cns.mac
contrib/maxima/eclean.mac
contrib/maxima/ecleanbase.mac
contrib/maxima/ehclean.mac
contrib/maxima/ehcleanbase.mac
contrib/maxima/em-modes.mac
contrib/maxima/em_units.mac
contrib/maxima/euler.mac
contrib/maxima/gedney-pml.mac
contrib/maxima/maxwell.mac
contrib/maxima/maxwellbase.mac
contrib/maxima/maxwellrectcav3d.mac
contrib/maxima/myhelpers.mac
contrib/maxima/pml.mac
contrib/maxima/wave.mac
contrib/notes/dumka3.cpp
contrib/notes/em-cheat.tm
contrib/notes/fluxfan.fig
contrib/notes/hedge-notes.tm
contrib/notes/ip-primal-nu.tm
contrib/notes/ip-primal.tm
contrib/notes/mystyle.ts
doc/Makefile
doc/conf.py
doc/discretization.rst
doc/index.rst
doc/misc.rst
doc/symbolic.rst
examples/dagrt-fusion.py
examples/geometry.py
examples/advection/surface.py
examples/advection/var-velocity.py
examples/advection/weak.py
examples/maxwell/cavities.py
examples/wave/var-propagation-speed.py
examples/wave/wave-eager-mpi.py
examples/wave/wave-eager-var-velocity.py
examples/wave/wave-eager.py
examples/wave/wave-min-mpi.py
examples/wave/wave-min.py
grudge/__init__.py
grudge/discretization.py
grudge/dt_finding.py
grudge/eager.py
grudge/execution.py
grudge/function_registry.py
grudge/shortcuts.py
grudge/tools.py
grudge/version.py
grudge.egg-info/PKG-INFO
grudge.egg-info/SOURCES.txt
grudge.egg-info/dependency_links.txt
grudge.egg-info/requires.txt
grudge.egg-info/top_level.txt
grudge/models/__init__.py
grudge/models/advection.py
grudge/models/burgers.py
grudge/models/diffusion.py
grudge/models/em.py
grudge/models/nd_calculus.py
grudge/models/pml.py
grudge/models/poisson.py
grudge/models/second_order.py
grudge/models/wave.py
grudge/models/gas_dynamics/__init__.py
grudge/models/gas_dynamics/lbm.py
grudge/symbolic/__init__.py
grudge/symbolic/compiler.py
grudge/symbolic/dofdesc_inference.py
grudge/symbolic/operators.py
grudge/symbolic/primitives.py
grudge/symbolic/tools.py
grudge/symbolic/mappers/__init__.py
test/mesh_data.py
test/test_grudge.py
test/test_mpi_communication.py